MANIFEST.in
README.md
setup.py
dmiyakawabadlogging/__init__.py
dmiyakawabadlogging.egg-info/PKG-INFO
dmiyakawabadlogging.egg-info/SOURCES.txt
dmiyakawabadlogging.egg-info/dependency_links.txt
dmiyakawabadlogging.egg-info/top_level.txt